chistes_gallegos/__init__.py
chistes_gallegos-1.0.data/scripts/tell-joke
chistes_gallegos-1.0.dist-info/METADATA
chistes_gallegos-1.0.dist-info/RECORD
chistes_gallegos-1.0.dist-info/WHEEL
chistes_gallegos-1.0.dist-info/top_level.txt
