Metadata-Version: 2.1
Name: chistes-gallegos
Version: 1.0
Summary: los mejores chistes gallegos
Home-page: https://github.com/victor-fdez/chistes-gallegos
Author: victor-fdez
Author-email: victor.j.fdez@gmail.com
License: MIT
Platform: UNKNOWN
Requires-Python: ~=3.6
